Workbook

Sheet Raw Data (Revenue)
A1: Segment | B1: FY 2023 | C1: FY 2024 | D1: FY 2025 | E1: YoY Growth 24 | F1: Yoy Growth 25 | G1: Revenue Mix % 2023 | H1: Revenue Mix % 2024 | I1: Revenue Mix % 2025 | J1: Segment Adjusted EBITDA (2023) | K1: Segment Adjusted EBITDA (2024) | L1: Segment Adjusted EBITDA (2025) | M1: Adj. EBITDA Margin (2023) | N1: Adj. EBITDA Margin (2024) | O1: Adj. EBITDA Margin (2025)
A2: Deliveries | B2: 1310 | C2: 1493 | D2: 1800 | E2: 0.14 | F2: 0.21 | G2: =B2/$B$6 -> 0.55532005 | H2: =C2/$C$6 -> 0.5337862 | I2: =D2/$D$6 -> 0.53412463 | J2: 81 | K2: 196 | L2: 287 | M2: =J2/B2 -> 0.061832061 | N2: =K2/C2 -> 0.1312793 | O2: =L2/D2 -> 0.15944444
A3: Mobility | B3: 871 | C3: 1047 | D3: 1219 | E3: 0.2 | F3: 0.16 | G3: =B3/$B$6 -> 0.36922425 | H3: =C3/$C$6 -> 0.37432964 | I3: =D3/$D$6 -> 0.36172107 | J3: 466 | K3: 569 | L3: 690 | M3: =J3/B3 -> 0.53501722 | N3: =K3/C3 -> 0.5434575 | O3: =L3/D3 -> 0.56603774
A4: Financial Services | B4: 177 | C4: 253 | D4: 347 | E4: 0.44 | F4: 0.37 | G4: =B4/$B$6 -> 0.075031793 | H4: =C4/$C$6 -> 0.090454058 | I4: =D4/$D$6 -> 0.10296736 | J4: -170 | K4: -105 | L4: -110 | M4: =J4/B4 -> -0.96045198 | N4: =K4/C4 -> -0.41501976 | O4: =L4/D4 -> -0.31700288
A5: Others | B5: 1 | C5: 4 | D5: 4 | E5: 1.66 | F5: 0.14 | G5: =B5/$B$6 -> 0.00042390844 | H5: =C5/$C$6 -> 0.0014301037 | I5: =D5/$D$6 -> 0.0011869436 | J5: -1 | K5: 3 | L5: 1 | M5: =J5/B5 -> -1 | N5: =K5/C5 -> 0.75 | O5: =L5/D5 -> 0.25
A6: Total | B6: =SUM(B2:B5) -> 2359 | C6: =SUM(C2:C5) -> 2797 | D6: =SUM(D2:D5) -> 3370 | G6: =SUM(G2:G5) -> 1 | H6: =SUM(H2:H5) -> 1 | I6: =SUM(I2:I5) -> 1
B8: FY 2023 | C8: FY 2024 | D8: FY 2025
A9: Deliveries | B9: =M2 -> 0.061832061 | C9: =N2 -> 0.1312793 | D9: =O2 -> 0.15944444
A10: Mobility | B10: =M3 -> 0.53501722 | C10: =N3 -> 0.5434575 | D10: =O3 -> 0.56603774
A11: Financial Services | B11: =M4 -> -0.96045198 | C11: =N4 -> -0.41501976 | D11: =O4 -> -0.31700288

Sheet Model
A1: Revenue Forecast
A2: Segment | B2: FY 2023 (Actual) | C2: FY 2024 (Actual) | D2: FY 2025 (Actual) | E2: FY 2026 Base Case | F2: FY 2026 Bear Case
A3: Deliveries | B3: ='Raw Data (Revenue)'!B2 -> 1310 | C3: ='Raw Data (Revenue)'!C2 -> 1493 | D3: ='Raw Data (Revenue)'!D2 -> 1800 | E3: =D3*(1+B11) -> 2178 | F3: =D3*(1+C11) -> 2064.6
A4: Mobility | B4: ='Raw Data (Revenue)'!B3 -> 871 | C4: ='Raw Data (Revenue)'!C3 -> 1047 | D4: ='Raw Data (Revenue)'!D3 -> 1219 | E4: =D4*(1+B12) -> 1414.04 | F4: =D4*(1+C12) -> 1355.528
A5: Financial Services | B5: ='Raw Data (Revenue)'!B4 -> 177 | C5: ='Raw Data (Revenue)'!C4 -> 253 | D5: ='Raw Data (Revenue)'!D4 -> 347 | E5: =D5*(1+B13) -> 475.39 | F5: =D5*(1+C13) -> 436.873
A6: Others | B6: ='Raw Data (Revenue)'!B5 -> 1 | C6: ='Raw Data (Revenue)'!C5 -> 4 | D6: ='Raw Data (Revenue)'!D5 -> 4 | E6: =D6*(1+B14) -> 4 | F6: =D6*(1+C14) -> 4
A7: Total | B7: =SUM(B3:B6) -> 2359 | C7: =SUM(C3:C6) -> 2797 | D7: =SUM(D3:D6) -> 3370 | E7: =SUM(E3:E6) -> 4071.43 | F7: =SUM(F3:F6) -> 3861.001
A9: Assumptions
A10: Segment | B10: Base Case Growth% | C10: Bear Case Growth %
A11: Deliveries | B11: 0.21 | C11: =B11-((B11*30)/100) -> 0.147
A12: Mobility | B12: 0.16 | C12: =B12-((B12*30)/100) -> 0.112
A13: Financial Services | B13: 0.37 | C13: =B13-((B13*30)/100) -> 0.259
A14: Others | B14: 0 | C14: =B14-((B14*30)/100) -> 0

Sheet Dashboard
A1: Grab Holdings — Financial Performance Dashboard
A2: Total FY2025 Revenue | C2: Fastest Growing Segment | E2: Most Profitable Segment | G2: FY 2026 Base Case Projection
A3: $3,370M | C3: Financial Services +37% | E3: Mobility 56.6% margin | G3: $4,071M

Sheet PBI_Data
